eventum_studio/01_Time_distribution.py
eventum_studio/__init__.py
eventum_studio/__main__.py
eventum_studio/components/component.py
eventum_studio/components/sample_explorer.py
eventum_studio/components/span_input.py
eventum_studio/components/template_configuration_editor.py
eventum_studio/components/template_editor.py
eventum_studio/components/template_manager.py
eventum_studio/components/template_renderer.py
eventum_studio/components/template_state_viewer.py
eventum_studio/components/time_pattern_configurator.py
eventum_studio/components/time_pattern_configurator_list.py
eventum_studio/components/time_pattern_distribution_histogram.py
eventum_studio/notifiers.py
eventum_studio/pages/02_Event_template.py
eventum_studio/py.typed
eventum_studio/static/favicon.ico
eventum_studio/theme.py
eventum_studio/utils/__init__.py
eventum_studio/utils/relative_time.py
eventum_studio/utils/tests/test_relative_time.py
eventum_studio/utils/validation_prettier.py
eventum_studio/widget_management.py
eventum_studio-1.1.0.dist-info/LICENSE
eventum_studio-1.1.0.dist-info/METADATA
eventum_studio-1.1.0.dist-info/WHEEL
eventum_studio-1.1.0.dist-info/entry_points.txt
eventum_studio-1.1.0.dist-info/RECORD
