Metadata-Version: 2.1
Name: eventum-studio
Version: 1.1.0
Summary: Content designer for Eventum 
Home-page: https://github.com/Eventum-Generatives/EventumStudio
License: Apache-2.0
Keywords: content,IDE,template,visualization
Author: Nikita Reznikov
Author-email: nikita.reznikov.public@mail.ru
Requires-Python: >=3.11,<4.0
Classifier: Development Status :: 5 - Production/Stable
Classifier: Intended Audience :: Developers
Classifier: License :: OSI Approved :: Apache Software License
Classifier: Operating System :: OS Independent
Classifier: Programming Language :: Python :: 3
Classifier: Programming Language :: Python :: 3.11
Classifier: Programming Language :: Python :: 3.12
Requires-Dist: eventum-content-manager (>=1.1.0,<2.0.0)
Requires-Dist: eventum-plugins (>=1.1.1,<2.0.0)
Requires-Dist: numpy (>=1.26.4,<2.0.0)
Requires-Dist: pandas (>=2.2.1,<3.0.0)
Requires-Dist: plotly (>=5.20.0,<6.0.0)
Requires-Dist: pydantic (>=2.6.2,<3.0.0)
Requires-Dist: pytz (>=2024.1,<2025.0)
Requires-Dist: streamlit (==1.28.1)
Requires-Dist: streamlit-elements (>=0.1.0,<0.2.0)
Requires-Dist: tzlocal (>=5.2,<6.0)
Project-URL: Documentation, https://eventum-generatives.github.io/Website/
Project-URL: Repository, https://github.com/Eventum-Generatives/EventumStudio
